quark_plugin_qrisp/__init__.py
quark_plugin_qrisp/mis_qiro_mapping_qrisp.py
quark_plugin_qrisp/qiro_ibm_device_qrisp.py
quark_plugin_qrisp/qiro_statevector_simulator_qrisp.py
quark_plugin_qrisp/utils.py
quark_plugin_qrisp-0.1.2.dist-info/licenses/LICENSE
quark_plugin_qrisp-0.1.2.dist-info/licenses/NOTICE
quark_plugin_qrisp-0.1.2.dist-info/METADATA
quark_plugin_qrisp-0.1.2.dist-info/WHEEL
quark_plugin_qrisp-0.1.2.dist-info/top_level.txt
quark_plugin_qrisp-0.1.2.dist-info/RECORD
